roax/geo.py
roax_geo-1.1.1.dist-info/LICENSE
roax_geo-1.1.1.dist-info/WHEEL
roax_geo-1.1.1.dist-info/METADATA
roax_geo-1.1.1.dist-info/RECORD
