Metadata-Version: 2.1
Name: roax-geo
Version: 1.1.1
Summary: Geographic extension for Roax.
Home-page: https://github.com/roax/roax-geo/
License: MIT
Keywords: wsgi,framework,resource,openapi
Author: Paul Bryan
Author-email: pbryan@anode.ca
Requires-Python: >=3.6,<3.8
Classifier: Development Status :: 5 - Production/Stable
Classifier: Intended Audience :: Developers
Classifier: License :: OSI Approved :: MIT License
Classifier: Programming Language :: Python :: 3
Classifier: Programming Language :: Python :: 3.6
Classifier: Programming Language :: Python :: 3.7
Classifier: Topic :: Internet :: WWW/HTTP :: WSGI :: Application
Requires-Dist: geomet (>=0.2,<0.3)
Requires-Dist: roax (>=1.9,<2.0)
Project-URL: Documentation, https://github.com/roax/roax-geo/wiki
